padmet/__init__.py
padmet/__main__.py
padmet/classes/__init__.py
padmet/classes/instantiation.py
padmet/classes/node.py
padmet/classes/padmetRef.py
padmet/classes/padmetSpec.py
padmet/classes/policy.py
padmet/classes/relation.py
padmet/utils/__init__.py
padmet/utils/gbr.py
padmet/utils/sbmlPlugin.py
padmet/utils/utils.py
padmet/utils/connection/__init__.py
padmet/utils/connection/biggAPI_to_padmet.py
padmet/utils/connection/check_orthology_input.py
padmet/utils/connection/enhanced_meneco_output.py
padmet/utils/connection/extract_orthofinder.py
padmet/utils/connection/extract_rxn_with_gene_assoc.py
padmet/utils/connection/gbk_to_faa.py
padmet/utils/connection/gene_to_targets.py
padmet/utils/connection/get_metacyc_ontology.py
padmet/utils/connection/metexploreviz_export.py
padmet/utils/connection/modelSeed_to_padmet.py
padmet/utils/connection/network_to_gnn.py
padmet/utils/connection/padmet_to_asp.py
padmet/utils/connection/padmet_to_matrix.py
padmet/utils/connection/padmet_to_padmet.py
padmet/utils/connection/padmet_to_tsv.py
padmet/utils/connection/pgdb_to_padmet.py
padmet/utils/connection/sbmlGenerator.py
padmet/utils/connection/sbml_to_curation_form.py
padmet/utils/connection/sbml_to_padmet.py
padmet/utils/connection/sbml_to_sbml.py
padmet/utils/connection/wikiGenerator.py
padmet/utils/exploration/__init__.py
padmet/utils/exploration/compare_padmet.py
padmet/utils/exploration/compare_sbml.py
padmet/utils/exploration/compare_sbml_padmet.py
padmet/utils/exploration/convert_sbml_db.py
padmet/utils/exploration/dendrogram_reactions_distance.py
padmet/utils/exploration/flux_analysis.py
padmet/utils/exploration/get_pwy_from_rxn.py
padmet/utils/exploration/padmet_stats.py
padmet/utils/exploration/pathway_production.py
padmet/utils/exploration/prot2genome.py
padmet/utils/exploration/report_network.py
padmet/utils/exploration/visu_network.py
padmet/utils/exploration/visu_path.py
padmet/utils/exploration/visu_similarity_gsmn.py
padmet/utils/management/__init__.py
padmet-5.0.3.dist-info/LICENSE
padmet-5.0.3.dist-info/METADATA
padmet-5.0.3.dist-info/WHEEL
padmet-5.0.3.dist-info/entry_points.txt
padmet-5.0.3.dist-info/top_level.txt
padmet-5.0.3.dist-info/RECORD
