Metadata-Version: 2.1
Name: padmet
Version: 5.0.3
Summary: The PADMet package allows conciliating genomics and metabolic network information used to produce a genome-scale constraint-based metabolic model within a database that traces all the reconstruction process steps. It allows representing the metabolic model in the form of a Wiki containing all the used/traced information. Other standard outputs are made available with the package.
Author-email: AuReMe <gem-aureme@inria.fr>
License: GPL-3.0-or-later
Project-URL: Homepage, https://github.com/AuReMe/padmet
Project-URL: Changelog, https://github.com/AuReMe/padmet/blob/main/CHANGELOG.md
License-File: LICENSE
Requires-Dist: docopt >=0.6.2
Requires-Dist: python-libsbml >=5.18.0
Requires-Dist: cobra >=0.17.1
Requires-Dist: biopython >=1.78
Requires-Dist: lxml >=4.3.4
